{
  "book": 54,
  "book_name": "1 Timothy",
  "chapter": 6,
  "start_verse": 9,
  "end_verse": 12,
  "verse_count": 4,
  "token_count": 79,
  "tokens": [
    {
      "verse": 9,
      "word_num": 1,
      "greek": "οἱ",
      "transliteration": "",
      "gloss": "the",
      "grammar_codes": [
        "ART",
        "NOM",
        "M",
        "P"
      ],
      "part_of_speech": "art",
      "lemma": "οἱ",
      "rmac": "T-NPM"
    },
    {
      "verse": 9,
      "word_num": 2,
      "greek": "δὲ",
      "transliteration": "",
      "gloss": "but",
      "grammar_codes": [
        "CONJ"
      ],
      "part_of_speech": "conj",
      "lemma": "δὲ",
      "rmac": "CONJ"
    },
    {
      "verse": 9,
      "word_num": 3,
      "greek": "βουλόμενοι",
      "transliteration": "",
      "gloss": "to wish",
      "grammar_codes": [
        "V",
        "PRES",
        "N",
        "PTCP",
        "NP",
        "P"
      ],
      "part_of_speech": "v",
      "lemma": "βουλόμενοι",
      "rmac": "V-PNP-NPM"
    },
    {
      "verse": 9,
      "word_num": 4,
      "greek": "πλουτεῖν",
      "transliteration": "",
      "gloss": "to be rich",
      "grammar_codes": [
        "V",
        "PRES",
        "ACT",
        "INF"
      ],
      "part_of_speech": "v",
      "lemma": "πλουτεῖν",
      "rmac": "V-PAN"
    },
    {
      "verse": 9,
      "word_num": 5,
      "greek": "ἐμπίπτουσιν",
      "transliteration": "",
      "gloss": "to fall into",
      "grammar_codes": [
        "V",
        "PRES",
        "ACT",
        "IND",
        "3P",
        "P"
      ],
      "part_of_speech": "v",
      "lemma": "ἐμπίπτουσιν",
      "rmac": "V-PAI-3P"
    },
    {
      "verse": 9,
      "word_num": 6,
      "greek": "εἰς",
      "transliteration": "",
      "gloss": "to",
      "grammar_codes": [
        "PREP"
      ],
      "part_of_speech": "prep",
      "lemma": "εἰς",
      "rmac": "PREP"
    },
    {
      "verse": 9,
      "word_num": 7,
      "greek": "πειρασμὸν",
      "transliteration": "",
      "gloss": "test",
      "grammar_codes": [
        "N",
        "ACC",
        "M",
        "S"
      ],
      "part_of_speech": "n",
      "lemma": "πειρασμὸν",
      "rmac": "N-ASM"
    },
    {
      "verse": 9,
      "word_num": 8,
      "greek": "καὶ",
      "transliteration": "",
      "gloss": "and",
      "grammar_codes": [
        "CONJ"
      ],
      "part_of_speech": "conj",
      "lemma": "καὶ",
      "rmac": "CONJ"
    },
    {
      "verse": 9,
      "word_num": 9,
      "greek": "παγίδα",
      "transliteration": "",
      "gloss": "trap",
      "grammar_codes": [
        "N",
        "ACC",
        "F",
        "S"
      ],
      "part_of_speech": "n",
      "lemma": "παγίδα",
      "rmac": "N-ASF"
    },
    {
      "verse": 9,
      "word_num": 10,
      "greek": "καὶ",
      "transliteration": "",
      "gloss": "and",
      "grammar_codes": [
        "CONJ"
      ],
      "part_of_speech": "conj",
      "lemma": "καὶ",
      "rmac": "CONJ"
    },
    {
      "verse": 9,
      "word_num": 11,
      "greek": "ἐπιθυμίας",
      "transliteration": "",
      "gloss": "desire",
      "grammar_codes": [
        "N",
        "ACC",
        "F",
        "P"
      ],
      "part_of_speech": "n",
      "lemma": "ἐπιθυμίας",
      "rmac": "N-APF"
    },
    {
      "verse": 9,
      "word_num": 12,
      "greek": "πολλὰς",
      "transliteration": "",
      "gloss": "many",
      "grammar_codes": [
        "ADJ",
        "ACC",
        "F",
        "P"
      ],
      "part_of_speech": "adj",
      "lemma": "πολλὰς",
      "rmac": "A-APF"
    },
    {
      "verse": 9,
      "word_num": 13,
      "greek": "ἀνοήτους",
      "transliteration": "",
      "gloss": "foolish",
      "grammar_codes": [
        "ADJ",
        "ACC",
        "F",
        "P"
      ],
      "part_of_speech": "adj",
      "lemma": "ἀνοήτους",
      "rmac": "A-APF"
    },
    {
      "verse": 9,
      "word_num": 14,
      "greek": "καὶ",
      "transliteration": "",
      "gloss": "and",
      "grammar_codes": [
        "CONJ"
      ],
      "part_of_speech": "conj",
      "lemma": "καὶ",
      "rmac": "CONJ"
    },
    {
      "verse": 9,
      "word_num": 15,
      "greek": "βλαβεράς",
      "transliteration": "",
      "gloss": "harmful",
      "grammar_codes": [
        "ADJ",
        "ACC",
        "F",
        "P"
      ],
      "part_of_speech": "adj",
      "lemma": "βλαβεράς",
      "rmac": "A-APF"
    },
    {
      "verse": 9,
      "word_num": 16,
      "greek": "αἵτινες",
      "transliteration": "",
      "gloss": "who",
      "grammar_codes": [
        "PRON",
        "NOM",
        "F",
        "P"
      ],
      "part_of_speech": "pron",
      "lemma": "αἵτινες",
      "rmac": "R-NPF"
    },
    {
      "verse": 9,
      "word_num": 17,
      "greek": "βυθίζουσιν",
      "transliteration": "",
      "gloss": "to plunge",
      "grammar_codes": [
        "V",
        "PRES",
        "ACT",
        "IND",
        "3P",
        "P"
      ],
      "part_of_speech": "v",
      "lemma": "βυθίζουσιν",
      "rmac": "V-PAI-3P"
    },
    {
      "verse": 9,
      "word_num": 18,
      "greek": "τοὺς",
      "transliteration": "",
      "gloss": "the",
      "grammar_codes": [
        "ART",
        "ACC",
        "M",
        "P"
      ],
      "part_of_speech": "art",
      "lemma": "τοὺς",
      "rmac": "T-APM"
    },
    {
      "verse": 9,
      "word_num": 19,
      "greek": "ἀνθρώπους",
      "transliteration": "",
      "gloss": "human being",
      "grammar_codes": [
        "N",
        "ACC",
        "M",
        "P"
      ],
      "part_of_speech": "n",
      "lemma": "ἀνθρώπους",
      "rmac": "N-APM"
    },
    {
      "verse": 9,
      "word_num": 20,
      "greek": "εἰς",
      "transliteration": "",
      "gloss": "to",
      "grammar_codes": [
        "PREP"
      ],
      "part_of_speech": "prep",
      "lemma": "εἰς",
      "rmac": "PREP"
    },
    {
      "verse": 9,
      "word_num": 21,
      "greek": "ὄλεθρον",
      "transliteration": "",
      "gloss": "destruction",
      "grammar_codes": [
        "N",
        "ACC",
        "M",
        "S"
      ],
      "part_of_speech": "n",
      "lemma": "ὄλεθρον",
      "rmac": "N-ASM"
    },
    {
      "verse": 9,
      "word_num": 22,
      "greek": "καὶ",
      "transliteration": "",
      "gloss": "and",
      "grammar_codes": [
        "CONJ"
      ],
      "part_of_speech": "conj",
      "lemma": "καὶ",
      "rmac": "CONJ"
    },
    {
      "verse": 9,
      "word_num": 23,
      "greek": "ἀπώλειαν",
      "transliteration": "",
      "gloss": "destruction",
      "grammar_codes": [
        "N",
        "ACC",
        "F",
        "S"
      ],
      "part_of_speech": "n",
      "lemma": "ἀπώλειαν",
      "rmac": "N-ASF"
    },
    {
      "verse": 10,
      "word_num": 1,
      "greek": "ῥίζα",
      "transliteration": "",
      "gloss": "root",
      "grammar_codes": [
        "N",
        "NOM",
        "F",
        "S"
      ],
      "part_of_speech": "n",
      "lemma": "ῥίζα",
      "rmac": "N-NSF"
    },
    {
      "verse": 10,
      "word_num": 2,
      "greek": "γὰρ",
      "transliteration": "",
      "gloss": "for",
      "grammar_codes": [
        "CONJ"
      ],
      "part_of_speech": "conj",
      "lemma": "γὰρ",
      "rmac": "CONJ"
    },
    {
      "verse": 10,
      "word_num": 3,
      "greek": "πάντων",
      "transliteration": "",
      "gloss": "all",
      "grammar_codes": [
        "ADJ",
        "GEN",
        "N",
        "P"
      ],
      "part_of_speech": "adj",
      "lemma": "πάντων",
      "rmac": "A-GPN"
    },
    {
      "verse": 10,
      "word_num": 4,
      "greek": "τῶν",
      "transliteration": "",
      "gloss": "the",
      "grammar_codes": [
        "ART",
        "GEN",
        "N",
        "P"
      ],
      "part_of_speech": "art",
      "lemma": "τῶν",
      "rmac": "T-GPN"
    },
    {
      "verse": 10,
      "word_num": 5,
      "greek": "κακῶν",
      "transliteration": "",
      "gloss": "evil",
      "grammar_codes": [
        "ADJ",
        "GEN",
        "N",
        "P"
      ],
      "part_of_speech": "adj",
      "lemma": "κακῶν",
      "rmac": "A-GPN"
    },
    {
      "verse": 10,
      "word_num": 6,
      "greek": "ἐστιν",
      "transliteration": "",
      "gloss": "to be",
      "grammar_codes": [
        "V",
        "PRES",
        "ACT",
        "IND",
        "3P",
        "S"
      ],
      "part_of_speech": "v",
      "lemma": "ἐστιν",
      "rmac": "V-PAI-3S"
    },
    {
      "verse": 10,
      "word_num": 7,
      "greek": "ἡ",
      "transliteration": "",
      "gloss": "the",
      "grammar_codes": [
        "ART",
        "NOM",
        "F",
        "S"
      ],
      "part_of_speech": "art",
      "lemma": "ἡ",
      "rmac": "T-NSF"
    },
    {
      "verse": 10,
      "word_num": 8,
      "greek": "φιλαργυρία",
      "transliteration": "",
      "gloss": "love of money",
      "grammar_codes": [
        "N",
        "NOM",
        "F",
        "S"
      ],
      "part_of_speech": "n",
      "lemma": "φιλαργυρία",
      "rmac": "N-NSF"
    },
    {
      "verse": 10,
      "word_num": 9,
      "greek": "ἧς",
      "transliteration": "",
      "gloss": "who",
      "grammar_codes": [
        "PRON",
        "GEN",
        "F",
        "S"
      ],
      "part_of_speech": "pron",
      "lemma": "ἧς",
      "rmac": "R-GSF"
    },
    {
      "verse": 10,
      "word_num": 10,
      "greek": "τινες",
      "transliteration": "",
      "gloss": "someone",
      "grammar_codes": [
        "PART"
      ],
      "part_of_speech": "part",
      "lemma": "τινες",
      "rmac": "X-NPM"
    },
    {
      "verse": 10,
      "word_num": 11,
      "greek": "ὀρεγόμενοι",
      "transliteration": "",
      "gloss": "to set one's heart on",
      "grammar_codes": [
        "V",
        "PRES",
        "MID",
        "PTCP",
        "NP",
        "P"
      ],
      "part_of_speech": "v",
      "lemma": "ὀρεγόμενοι",
      "rmac": "V-PMP-NPM"
    },
    {
      "verse": 10,
      "word_num": 12,
      "greek": "ἀπεπλανήθησαν",
      "transliteration": "",
      "gloss": "to deceive",
      "grammar_codes": [
        "V",
        "AOR",
        "PASS",
        "IND",
        "3P",
        "P"
      ],
      "part_of_speech": "v",
      "lemma": "ἀπεπλανήθησαν",
      "rmac": "V-API-3P"
    },
    {
      "verse": 10,
      "word_num": 13,
      "greek": "ἀπὸ",
      "transliteration": "",
      "gloss": "from",
      "grammar_codes": [
        "PREP"
      ],
      "part_of_speech": "prep",
      "lemma": "ἀπὸ",
      "rmac": "PREP"
    },
    {
      "verse": 10,
      "word_num": 14,
      "greek": "τῆς",
      "transliteration": "",
      "gloss": "the",
      "grammar_codes": [
        "ART",
        "GEN",
        "F",
        "S"
      ],
      "part_of_speech": "art",
      "lemma": "τῆς",
      "rmac": "T-GSF"
    },
    {
      "verse": 10,
      "word_num": 15,
      "greek": "πίστεως",
      "transliteration": "",
      "gloss": "faith",
      "grammar_codes": [
        "N",
        "GEN",
        "F",
        "S"
      ],
      "part_of_speech": "n",
      "lemma": "πίστεως",
      "rmac": "N-GSF"
    },
    {
      "verse": 10,
      "word_num": 16,
      "greek": "καὶ",
      "transliteration": "",
      "gloss": "and",
      "grammar_codes": [
        "CONJ"
      ],
      "part_of_speech": "conj",
      "lemma": "καὶ",
      "rmac": "CONJ"
    },
    {
      "verse": 10,
      "word_num": 17,
      "greek": "ἑαυτοὺς",
      "transliteration": "",
      "gloss": "himself",
      "grammar_codes": [
        "F"
      ],
      "part_of_speech": "f",
      "lemma": "ἑαυτοὺς",
      "rmac": "F-3APM"
    },
    {
      "verse": 10,
      "word_num": 18,
      "greek": "περιέπειραν",
      "transliteration": "",
      "gloss": "to pierce",
      "grammar_codes": [
        "V",
        "AOR",
        "ACT",
        "IND",
        "3P",
        "P"
      ],
      "part_of_speech": "v",
      "lemma": "περιέπειραν",
      "rmac": "V-AAI-3P"
    },
    {
      "verse": 10,
      "word_num": 19,
      "greek": "ὀδύναις",
      "transliteration": "",
      "gloss": "anguish",
      "grammar_codes": [
        "N",
        "DAT",
        "F",
        "P"
      ],
      "part_of_speech": "n",
      "lemma": "ὀδύναις",
      "rmac": "N-DPF"
    },
    {
      "verse": 10,
      "word_num": 20,
      "greek": "πολλαῖς",
      "transliteration": "",
      "gloss": "many",
      "grammar_codes": [
        "ADJ",
        "DAT",
        "F",
        "P"
      ],
      "part_of_speech": "adj",
      "lemma": "πολλαῖς",
      "rmac": "A-DPF"
    },
    {
      "verse": 11,
      "word_num": 1,
      "greek": "Σὺ",
      "transliteration": "",
      "gloss": "you",
      "grammar_codes": [
        "PREP"
      ],
      "part_of_speech": "prep",
      "lemma": "Σὺ",
      "rmac": "P-2NS"
    },
    {
      "verse": 11,
      "word_num": 2,
      "greek": "δέ",
      "transliteration": "",
      "gloss": "but",
      "grammar_codes": [
        "CONJ"
      ],
      "part_of_speech": "conj",
      "lemma": "δέ",
      "rmac": "CONJ"
    },
    {
      "verse": 11,
      "word_num": 3,
      "greek": "ὦ",
      "transliteration": "",
      "gloss": "Oh!",
      "grammar_codes": [
        "INTERJ"
      ],
      "part_of_speech": "interj",
      "lemma": "ὦ",
      "rmac": "INJ"
    },
    {
      "verse": 11,
      "word_num": 4,
      "greek": "ἄνθρωπε",
      "transliteration": "",
      "gloss": "human being",
      "grammar_codes": [
        "N",
        "VOC",
        "M",
        "S"
      ],
      "part_of_speech": "n",
      "lemma": "ἄνθρωπε",
      "rmac": "N-VSM"
    },
    {
      "verse": 11,
      "word_num": 5,
      "greek": "θεοῦ",
      "transliteration": "",
      "gloss": "God",
      "grammar_codes": [
        "N",
        "GEN",
        "M",
        "S"
      ],
      "part_of_speech": "n",
      "lemma": "θεοῦ",
      "rmac": "N-GSM"
    },
    {
      "verse": 11,
      "word_num": 6,
      "greek": "ταῦτα",
      "transliteration": "",
      "gloss": "this",
      "grammar_codes": [
        "ADV"
      ],
      "part_of_speech": "adv",
      "lemma": "ταῦτα",
      "rmac": "D-APN"
    },
    {
      "verse": 11,
      "word_num": 7,
      "greek": "φεῦγε",
      "transliteration": "",
      "gloss": "flee",
      "grammar_codes": [
        "V",
        "PRES",
        "ACT",
        "IMP",
        "2P",
        "S"
      ],
      "part_of_speech": "v",
      "lemma": "φεῦγε",
      "rmac": "V-PAM-2S"
    },
    {
      "verse": 11,
      "word_num": 8,
      "greek": "δίωκε",
      "transliteration": "",
      "gloss": "to pursue",
      "grammar_codes": [
        "V",
        "PRES",
        "ACT",
        "IMP",
        "2P",
        "S"
      ],
      "part_of_speech": "v",
      "lemma": "δίωκε",
      "rmac": "V-PAM-2S"
    },
    {
      "verse": 11,
      "word_num": 9,
      "greek": "δὲ",
      "transliteration": "",
      "gloss": "but",
      "grammar_codes": [
        "CONJ"
      ],
      "part_of_speech": "conj",
      "lemma": "δὲ",
      "rmac": "CONJ"
    },
    {
      "verse": 11,
      "word_num": 10,
      "greek": "δικαιοσύνην",
      "transliteration": "",
      "gloss": "righteousness",
      "grammar_codes": [
        "N",
        "ACC",
        "F",
        "S"
      ],
      "part_of_speech": "n",
      "lemma": "δικαιοσύνην",
      "rmac": "N-ASF"
    },
    {
      "verse": 11,
      "word_num": 11,
      "greek": "εὐσέβειαν",
      "transliteration": "",
      "gloss": "godliness",
      "grammar_codes": [
        "N",
        "ACC",
        "F",
        "S"
      ],
      "part_of_speech": "n",
      "lemma": "εὐσέβειαν",
      "rmac": "N-ASF"
    },
    {
      "verse": 11,
      "word_num": 12,
      "greek": "πίστιν",
      "transliteration": "",
      "gloss": "faith",
      "grammar_codes": [
        "N",
        "ACC",
        "F",
        "S"
      ],
      "part_of_speech": "n",
      "lemma": "πίστιν",
      "rmac": "N-ASF"
    },
    {
      "verse": 11,
      "word_num": 13,
      "greek": "ἀγάπην",
      "transliteration": "",
      "gloss": "love",
      "grammar_codes": [
        "N",
        "ACC",
        "F",
        "S"
      ],
      "part_of_speech": "n",
      "lemma": "ἀγάπην",
      "rmac": "N-ASF"
    },
    {
      "verse": 11,
      "word_num": 14,
      "greek": "ὑπομονὴν",
      "transliteration": "",
      "gloss": "perseverance",
      "grammar_codes": [
        "N",
        "ACC",
        "F",
        "S"
      ],
      "part_of_speech": "n",
      "lemma": "ὑπομονὴν",
      "rmac": "N-ASF"
    },
    {
      "verse": 11,
      "word_num": 15,
      "greek": "πραϋπαθίαν",
      "transliteration": "",
      "gloss": "gentleness",
      "grammar_codes": [
        "N",
        "ACC",
        "F",
        "S"
      ],
      "part_of_speech": "n",
      "lemma": "πραϋπαθίαν",
      "rmac": "N-ASF"
    },
    {
      "verse": 12,
      "word_num": 1,
      "greek": "ἀγωνίζου",
      "transliteration": "",
      "gloss": "to fight",
      "grammar_codes": [
        "V",
        "PRES",
        "N",
        "IMP",
        "2P",
        "S"
      ],
      "part_of_speech": "v",
      "lemma": "ἀγωνίζου",
      "rmac": "V-PNM-2S"
    },
    {
      "verse": 12,
      "word_num": 2,
      "greek": "τὸν",
      "transliteration": "",
      "gloss": "the",
      "grammar_codes": [
        "ART",
        "ACC",
        "M",
        "S"
      ],
      "part_of_speech": "art",
      "lemma": "τὸν",
      "rmac": "T-ASM"
    },
    {
      "verse": 12,
      "word_num": 3,
      "greek": "καλὸν",
      "transliteration": "",
      "gloss": "good",
      "grammar_codes": [
        "ADJ",
        "ACC",
        "M",
        "S"
      ],
      "part_of_speech": "adj",
      "lemma": "καλὸν",
      "rmac": "A-ASM"
    },
    {
      "verse": 12,
      "word_num": 4,
      "greek": "ἀγῶνα",
      "transliteration": "",
      "gloss": "struggle",
      "grammar_codes": [
        "N",
        "ACC",
        "M",
        "S"
      ],
      "part_of_speech": "n",
      "lemma": "ἀγῶνα",
      "rmac": "N-ASM"
    },
    {
      "verse": 12,
      "word_num": 5,
      "greek": "τῆς",
      "transliteration": "",
      "gloss": "the",
      "grammar_codes": [
        "ART",
        "GEN",
        "F",
        "S"
      ],
      "part_of_speech": "art",
      "lemma": "τῆς",
      "rmac": "T-GSF"
    },
    {
      "verse": 12,
      "word_num": 6,
      "greek": "πίστεως",
      "transliteration": "",
      "gloss": "faith",
      "grammar_codes": [
        "N",
        "GEN",
        "F",
        "S"
      ],
      "part_of_speech": "n",
      "lemma": "πίστεως",
      "rmac": "N-GSF"
    },
    {
      "verse": 12,
      "word_num": 7,
      "greek": "ἐπιλαβοῦ",
      "transliteration": "",
      "gloss": "to take hold",
      "grammar_codes": [
        "V",
        "2",
        "ACT",
        "D",
        "2P",
        "S"
      ],
      "part_of_speech": "v",
      "lemma": "ἐπιλαβοῦ",
      "rmac": "V-2ADM-2S"
    },
    {
      "verse": 12,
      "word_num": 8,
      "greek": "τῆς",
      "transliteration": "",
      "gloss": "the",
      "grammar_codes": [
        "ART",
        "GEN",
        "F",
        "S"
      ],
      "part_of_speech": "art",
      "lemma": "τῆς",
      "rmac": "T-GSF"
    },
    {
      "verse": 12,
      "word_num": 9,
      "greek": "αἰωνίου",
      "transliteration": "",
      "gloss": "eternal",
      "grammar_codes": [
        "ADJ",
        "GEN",
        "F",
        "S"
      ],
      "part_of_speech": "adj",
      "lemma": "αἰωνίου",
      "rmac": "A-GSF"
    },
    {
      "verse": 12,
      "word_num": 10,
      "greek": "ζωῆς",
      "transliteration": "",
      "gloss": "life",
      "grammar_codes": [
        "N",
        "GEN",
        "F",
        "S"
      ],
      "part_of_speech": "n",
      "lemma": "ζωῆς",
      "rmac": "N-GSF"
    },
    {
      "verse": 12,
      "word_num": 11,
      "greek": "εἰς",
      "transliteration": "",
      "gloss": "to",
      "grammar_codes": [
        "PREP"
      ],
      "part_of_speech": "prep",
      "lemma": "εἰς",
      "rmac": "PREP"
    },
    {
      "verse": 12,
      "word_num": 12,
      "greek": "ἣν",
      "transliteration": "",
      "gloss": "who",
      "grammar_codes": [
        "PRON",
        "ACC",
        "F",
        "S"
      ],
      "part_of_speech": "pron",
      "lemma": "ἣν",
      "rmac": "R-ASF"
    },
    {
      "verse": 12,
      "word_num": 13,
      "greek": "ἐκλήθης",
      "transliteration": "",
      "gloss": "to call",
      "grammar_codes": [
        "V",
        "AOR",
        "PASS",
        "IND",
        "2P",
        "S"
      ],
      "part_of_speech": "v",
      "lemma": "ἐκλήθης",
      "rmac": "V-API-2S"
    },
    {
      "verse": 12,
      "word_num": 14,
      "greek": "καὶ",
      "transliteration": "",
      "gloss": "and",
      "grammar_codes": [
        "CONJ"
      ],
      "part_of_speech": "conj",
      "lemma": "καὶ",
      "rmac": "CONJ"
    },
    {
      "verse": 12,
      "word_num": 15,
      "greek": "ὡμολόγησας",
      "transliteration": "",
      "gloss": "to confess",
      "grammar_codes": [
        "V",
        "AOR",
        "ACT",
        "IND",
        "2P",
        "S"
      ],
      "part_of_speech": "v",
      "lemma": "ὡμολόγησας",
      "rmac": "V-AAI-2S"
    },
    {
      "verse": 12,
      "word_num": 16,
      "greek": "τὴν",
      "transliteration": "",
      "gloss": "the",
      "grammar_codes": [
        "ART",
        "ACC",
        "F",
        "S"
      ],
      "part_of_speech": "art",
      "lemma": "τὴν",
      "rmac": "T-ASF"
    },
    {
      "verse": 12,
      "word_num": 17,
      "greek": "καλὴν",
      "transliteration": "",
      "gloss": "good",
      "grammar_codes": [
        "ADJ",
        "ACC",
        "F",
        "S"
      ],
      "part_of_speech": "adj",
      "lemma": "καλὴν",
      "rmac": "A-ASF"
    },
    {
      "verse": 12,
      "word_num": 18,
      "greek": "ὁμολογίαν",
      "transliteration": "",
      "gloss": "confession",
      "grammar_codes": [
        "N",
        "ACC",
        "F",
        "S"
      ],
      "part_of_speech": "n",
      "lemma": "ὁμολογίαν",
      "rmac": "N-ASF"
    },
    {
      "verse": 12,
      "word_num": 19,
      "greek": "ἐνώπιον",
      "transliteration": "",
      "gloss": "before",
      "grammar_codes": [
        "PREP"
      ],
      "part_of_speech": "prep",
      "lemma": "ἐνώπιον",
      "rmac": "PREP"
    },
    {
      "verse": 12,
      "word_num": 20,
      "greek": "πολλῶν",
      "transliteration": "",
      "gloss": "many",
      "grammar_codes": [
        "ADJ",
        "GEN",
        "M",
        "P"
      ],
      "part_of_speech": "adj",
      "lemma": "πολλῶν",
      "rmac": "A-GPM"
    },
    {
      "verse": 12,
      "word_num": 21,
      "greek": "μαρτύρων",
      "transliteration": "",
      "gloss": "witness",
      "grammar_codes": [
        "N",
        "GEN",
        "M",
        "P"
      ],
      "part_of_speech": "n",
      "lemma": "μαρτύρων",
      "rmac": "N-GPM"
    }
  ]
}